mygeotab/__init__.py
mygeotab/api.py
mygeotab/api_async.py
mygeotab/cli.py
mygeotab/dates.py
mygeotab/exceptions.py
mygeotab/parameters.py
mygeotab/serializers.py
mygeotab/altitude/__init__.py
mygeotab/altitude/daas_definition.py
mygeotab/altitude/wrapper.py
mygeotab/ext/__init__.py
mygeotab/ext/entitylist.py
mygeotab/ext/feed.py
mygeotab-0.9.4.dist-info/licenses/LICENSE
mygeotab-0.9.4.dist-info/METADATA
mygeotab-0.9.4.dist-info/WHEEL
mygeotab-0.9.4.dist-info/entry_points.txt
mygeotab-0.9.4.dist-info/top_level.txt
mygeotab-0.9.4.dist-info/RECORD
