Metadata-Version: 2.4
Name: mygeotab
Version: 0.9.4
Summary: A Python client for the MyGeotab SDK
Home-page: https://github.com/geotab/mygeotab-python
Author: Geotab Inc.
License: Apache 2.0
Classifier: Development Status :: 4 - Beta
Classifier: Intended Audience :: Developers
Classifier: Natural Language :: English
Classifier: License :: OSI Approved :: Apache Software License
Classifier: Programming Language :: Python
Classifier: Programming Language :: Python :: 3.9
Classifier: Programming Language :: Python :: 3.10
Classifier: Programming Language :: Python :: 3.11
Classifier: Programming Language :: Python :: 3.12
Classifier: Programming Language :: Python :: 3.13
Classifier: Programming Language :: Python :: Implementation :: PyPy
Classifier: Topic :: Software Development :: Libraries
License-File: LICENSE
Requires-Dist: requests
Requires-Dist: urllib3
Requires-Dist: click
Requires-Dist: pytz
Requires-Dist: arrow
Requires-Dist: aiohttp[speedups]<4,>=3.12.2
Requires-Dist: python-rapidjson
Provides-Extra: notebook
Requires-Dist: pandas; extra == "notebook"
Dynamic: author
Dynamic: classifier
Dynamic: description
Dynamic: home-page
Dynamic: license
Dynamic: license-file
Dynamic: provides-extra
Dynamic: requires-dist
Dynamic: summary
